bollards/__init__.py
bollards-0.0.2.dist-info/METADATA
bollards-0.0.2.dist-info/WHEEL
bollards-0.0.2.dist-info/licenses/LICENSE
bollards-0.0.2.dist-info/RECORD
